ebank/__init__.py
ebank/balance.py
ebank/constants.py
ebank/factory.py
ebank/receipt.py
ebank/trans.py
ebank/utils/__init__.py
ebank/utils/baiduocr.py
ebank/utils/chaojiying.py
ebank/utils/filesearch.py
ebank/utils/sfun.py
utils/__init__.py
utils/baiduocr.py
utils/chaojiying.py
utils/filesearch.py
utils/misc.py
utils/sfun.py
ebank-2023.6.8.4.dist-info/METADATA
ebank-2023.6.8.4.dist-info/WHEEL
ebank-2023.6.8.4.dist-info/top_level.txt
ebank-2023.6.8.4.dist-info/RECORD
