Metadata-Version: 2.1
Name: ebank
Version: 2023.6.8.4
Requires-Dist: xlwt (>=1.3.0)
Requires-Dist: xlrd (==1.2.0)
Requires-Dist: pdfplumber (>=0.8.0)
Requires-Dist: encoo (==2023.6.8)
Requires-Dist: python-dateutil (>=2.8.2)
Requires-Dist: pypdf (>=3.6.0)
Requires-Dist: requests (>=2.28.2)
Requires-Dist: urllib3 (>=1.26.14)
